influxdump/__about__.py
influxdump/__init__.py
influxdump/data.py
influxdump/db.py
influxdump/exception.py
influxdump/exceptions.py
influxdump/bin/__init__.py
influxdump/bin/castcheck.py
influxdump/bin/influxdump.py
influxdump/bin/recast.py
influxdump-1.0.7.dist-info/LICENSE
influxdump-1.0.7.dist-info/METADATA
influxdump-1.0.7.dist-info/WHEEL
influxdump-1.0.7.dist-info/entry_points.txt
influxdump-1.0.7.dist-info/top_level.txt
influxdump-1.0.7.dist-info/RECORD
