Metadata-Version: 2.1
Name: influxdump
Version: 1.0.7
Summary: InfluxDB data backup tool
Home-page: https://github.com/gams/influxdump
Author: Stefan Berder <stefan@measureofquality.com>
Author-email: code+influxdump@measureofquality.com
License: Apache License, Version 2.0
Keywords: influxdb
Platform: UNKNOWN
Classifier: Development Status :: 3 - Alpha
Classifier: Environment :: Console
Classifier: Programming Language :: Python :: 2.7
Classifier: Programming Language :: Python :: 3.3
Requires-Dist: certifi ==2019.9.11
Requires-Dist: chardet ==3.0.4
Requires-Dist: idna ==2.8
Requires-Dist: influxdb ==5.3.1
Requires-Dist: msgpack ==0.6.1
Requires-Dist: python-dateutil ==2.6.0
Requires-Dist: pytz ==2016.10
Requires-Dist: requests ==2.22.0
Requires-Dist: six ==1.10.0
Requires-Dist: urllib3 ==1.25.3
